simpel/__init__.py
simpel/utils.py
simpel/version.py
simpel/simpel_accounts/__init__.py
simpel/simpel_accounts/admin.py
simpel/simpel_accounts/apps.py
simpel/simpel_accounts/exceptions.py
simpel/simpel_accounts/managers.py
simpel/simpel_accounts/models.py
simpel/simpel_accounts/settings.py
simpel/simpel_accounts/setup.py
simpel/simpel_accounts/signals.py
simpel/simpel_accounts/utils.py
simpel/simpel_accounts/views.py
simpel/simpel_accounts/management/__init__.py
simpel/simpel_accounts/management/commands/__init__.py
simpel/simpel_accounts/management/commands/close_expired_accounts.py
simpel/simpel_accounts/management/commands/init_accounts.py
simpel/simpel_accounts/management/commands/update_balance.py
simpel/simpel_accounts/migrations/0001_initial.py
simpel/simpel_accounts/migrations/__init__.py
simpel/simpel_accounts/tests/__init__.py
simpel/simpel_accounts/tests/factories.py
simpel/simpel_accounts/tests/tests_api.py
simpel/simpel_accounts/tests/tests_models.py
simpel/simpel_accounts/tests/tests_views.py
simpel/simpel_admin/apps.py
simpel/simpel_admin/base.py
simpel/simpel_admin/filters.py
simpel/simpel_admin/mixins.py
simpel/simpel_admin/settings.py
simpel/simpel_admin/sites.py
simpel/simpel_admin/static/simpel_admin/js/alpine.min.js
simpel/simpel_admin/static/simpel_admin/js/htmx.min.js
simpel/simpel_admin/static/simpel_admin/js/jquery.min.js
simpel/simpel_admin/templates/admin/base.html
simpel/simpel_admin/templates/admin/confirmation.html
simpel/simpel_admin/templates/admin/form_view.html
simpel/simpel_admin/templates/admin/inspect.html
simpel/simpel_admin/templates/admin/inspect_object_tools.html
simpel/simpel_admin/templates/admin/object_buttons.html
simpel/simpel_admin/templates/admin/print.html
simpel/simpel_admin/templates/admin/print_cover.html
simpel/simpel_admin/templates/admin/print_footer.html
simpel/simpel_admin/templates/admin/print_header.html
simpel/simpel_admin/tests/__init__.py
simpel/simpel_api/__init__.py
simpel/simpel_api/permissions.py
simpelerp-1.0.4.dist-info/LICENSE
simpelerp-1.0.4.dist-info/METADATA
simpelerp-1.0.4.dist-info/WHEEL
simpelerp-1.0.4.dist-info/top_level.txt
simpelerp-1.0.4.dist-info/RECORD
