Metadata-Version: 2.1
Name: simpelerp
Version: 1.0.4
Summary: Simple djang based ERP
Home-page: https://gitlab.com/sasri.works/simpel
Author: Rizki Sasri Dwitama
Author-email: sasri.works@gmail.com
License: MIT
Project-URL: Documentation, https://www.rizkisasri.com/projects/simpel/
Project-URL: Source, https://gitlab.com/sasri.works/simpel
Platform: UNKNOWN
Classifier: Environment :: Web Environment
Classifier: Framework :: Django
Classifier: Intended Audience :: Developers
Classifier: License :: OSI Approved :: MIT License
Classifier: Operating System :: OS Independent
Classifier: Programming Language :: Python
Classifier: Programming Language :: Python :: 3
Classifier: Programming Language :: Python :: 3 :: Only
Classifier: Programming Language :: Python :: 3.8
Classifier: Programming Language :: Python :: 3.9
Classifier: Topic :: Internet :: WWW/HTTP
Classifier: Topic :: Internet :: WWW/HTTP :: Dynamic Content
Classifier: Topic :: Internet :: WWW/HTTP :: WSGI
Classifier: Topic :: Software Development :: Libraries :: Python Modules
Classifier: Topic :: Software Development :: Libraries :: Application Frameworks
Requires-Python: >=3.6
License-File: LICENSE
Requires-Dist: django (<4.0,>=3.2.7)
Requires-Dist: django-rq
Requires-Dist: django-redis
Requires-Dist: django-allauth
Requires-Dist: django-mptt
Requires-Dist: django-taggit
Requires-Dist: django-filter
Requires-Dist: django-filer
Requires-Dist: django-qrcodes
Requires-Dist: django-hookup
Requires-Dist: django-numerators
Requires-Dist: django-ckeditor
Requires-Dist: django-select2
Requires-Dist: django-sekizai
Requires-Dist: django-comments-xtd
Requires-Dist: django-nested-admin
Requires-Dist: django-polymorphic
Requires-Dist: django-wkhtmltopdf
Requires-Dist: django-rest-polymorphic
Requires-Dist: django-import-export
Requires-Dist: django-extensions
Requires-Dist: django-phonenumber-field[phonenumbers]
Requires-Dist: drf-spectacular[sidecar]
Requires-Dist: easy-thumbnails
Requires-Dist: l18n
Requires-Dist: pytz
Requires-Dist: docutils
Requires-Dist: factory-boy
Provides-Extra: cms
Requires-Dist: django-cms ; extra == 'cms'
Requires-Dist: django-sekizai ; extra == 'cms'
Requires-Dist: djangocms-text-ckeditor ; extra == 'cms'
